mytopsis503/topsis.py
mytopsis503-0.5.dist-info/LICENSE.txt
mytopsis503-0.5.dist-info/METADATA
mytopsis503-0.5.dist-info/WHEEL
mytopsis503-0.5.dist-info/entry_points.txt
mytopsis503-0.5.dist-info/top_level.txt
mytopsis503-0.5.dist-info/RECORD
