Metadata-Version: 2.1
Name: mytopsis503
Version: 0.5
Summary: Topsis package to check which model is better
Home-page: UNKNOWN
Author: Shashwat Srivastava
Author-email: shashwatsrivastava348@gmail.com
License: MIT
Keywords: topsis,Thapar,Data_analytics
Platform: UNKNOWN
Classifier: Development Status :: 3 - Alpha
Classifier: Intended Audience :: Developers
Classifier: Topic :: Software Development :: Build Tools
Classifier: License :: OSI Approved :: MIT License
Classifier: Programming Language :: Python :: 3
Classifier: Programming Language :: Python :: 3.7
Requires-Dist: numpy
Requires-Dist: pandas
